qutepart/__init__.py
qutepart/bookmarks.py
qutepart/brackethlighter.py
qutepart/completer.py
qutepart/htmldelegate.py
qutepart/lines.py
qutepart/margins.py
qutepart/rectangularselection.py
qutepart/sideareas.py
qutepart/syntaxhlighter.py
qutepart/version.py
qutepart/vim.py
qutepart/indenter/__init__.py
qutepart/indenter/base.py
qutepart/indenter/cstyle.py
qutepart/indenter/lisp.py
qutepart/indenter/python.py
qutepart/indenter/ruby.py
qutepart/indenter/scheme.py
qutepart/indenter/xmlindent.py
qutepart/syntax/__init__.py
qutepart/syntax/colortheme.py
qutepart/syntax/loader.py
qutepart/syntax/parser.py
qutepart/syntax/data/syntax_db.json
qutepart/syntax/data/xml/4dos.xml
qutepart/syntax/data/xml/abap.xml
qutepart/syntax/data/xml/abc.xml
qutepart/syntax/data/xml/actionscript.xml
qutepart/syntax/data/xml/ada.xml
qutepart/syntax/data/xml/adblock.xml
qutepart/syntax/data/xml/agda.xml
qutepart/syntax/data/xml/ahdl.xml
qutepart/syntax/data/xml/ahk.xml
qutepart/syntax/data/xml/alert.xml
qutepart/syntax/data/xml/alert_indent.xml
qutepart/syntax/data/xml/ample.xml
qutepart/syntax/data/xml/ansforth94.xml
qutepart/syntax/data/xml/ansic89.xml
qutepart/syntax/data/xml/ansys.xml
qutepart/syntax/data/xml/apache.xml
qutepart/syntax/data/xml/apparmor.xml
qutepart/syntax/data/xml/asm-avr.xml
qutepart/syntax/data/xml/asm-dsp56k.xml
qutepart/syntax/data/xml/asm-m68k.xml
qutepart/syntax/data/xml/asm6502.xml
qutepart/syntax/data/xml/asn1.xml
qutepart/syntax/data/xml/asp.xml
qutepart/syntax/data/xml/asterisk.xml
qutepart/syntax/data/xml/awk.xml
qutepart/syntax/data/xml/bash.xml
qutepart/syntax/data/xml/bibtex.xml
qutepart/syntax/data/xml/bitbake.xml
qutepart/syntax/data/xml/bmethod.xml
qutepart/syntax/data/xml/boo.xml
qutepart/syntax/data/xml/c.xml
qutepart/syntax/data/xml/carto-css.xml
qutepart/syntax/data/xml/ccss.xml
qutepart/syntax/data/xml/cg.xml
qutepart/syntax/data/xml/cgis.xml
qutepart/syntax/data/xml/changelog.xml
qutepart/syntax/data/xml/chicken.xml
qutepart-3.3.3.dist-info/LICENSE
qutepart-3.3.3.dist-info/METADATA
qutepart-3.3.3.dist-info/WHEEL
qutepart-3.3.3.dist-info/top_level.txt
qutepart-3.3.3.dist-info/RECORD
