Metadata-Version: 2.1
Name: qutepart
Version: 3.3.3
Summary: Code editor component for PyQt5
Home-page: https://github.com/andreikop/qutepart
Author: Andrei Kopats
Author-email: andrei.kopats@gmail.com
License: GNU Lesser General Public License v2 or later (LGPLv2+)
Platform: UNKNOWN
Classifier: Development Status :: 5 - Production/Stable
Classifier: Intended Audience :: Developers
Classifier: License :: OSI Approved :: GNU Lesser General Public License v2 or later (LGPLv2+)
Classifier: Programming Language :: Python :: 3.5
Classifier: Programming Language :: Python :: 3.6
Classifier: Programming Language :: Python :: 3.7
Requires-Python: >=3.5
License-File: LICENSE
